roswagger/__init__.py
roswagger-2.0.dist-info/METADATA
roswagger-2.0.dist-info/WHEEL
roswagger-2.0.dist-info/top_level.txt
roswagger-2.0.dist-info/RECORD
